django_compose_settings/__init__.py
django_compose_settings/etc.py
django_compose_settings/modules.py
django_compose_settings-0.3.dist-info/AUTHORS
django_compose_settings-0.3.dist-info/LICENSE
django_compose_settings-0.3.dist-info/METADATA
django_compose_settings-0.3.dist-info/WHEEL
django_compose_settings-0.3.dist-info/top_level.txt
django_compose_settings-0.3.dist-info/RECORD
