Metadata-Version: 2.1
Name: django-compose-settings
Version: 0.3
Summary: Django composable settings loader.
Home-page: https://github.com/novafloss/django-compose-settings
Author: PeopleDoc
Author-email: rd@novapost.fr
License: MIT
Keywords: django,settings
Platform: UNKNOWN
Classifier: Development Status :: 4 - Beta
Classifier: Environment :: Console
Classifier: Intended Audience :: Developers
Classifier: License :: OSI Approved :: MIT License
Classifier: Programming Language :: Python
Provides-Extra: release
Requires-Dist: wheel ; extra == 'release'
Requires-Dist: zest.releaser ; extra == 'release'
